{
  "creds": {
    "noiseKey": {
      "private": {
        "type": "Buffer",
        "data": "6JFLJPJ/OiCnQWUQgymOJ79E3H5sH81gb2P1q2ykR3U="
      },
      "public": {
        "type": "Buffer",
        "data": "6MK9AAiq0OPnC7vPX9uPa3y2pAUzkgLQgUAXH9/5fQs="
      }
    },
    "signedIdentityKey": {
      "private": {
        "type": "Buffer",
        "data": "AORUvZwbvEl794dwDS+VQjW7unvpn0nDRoyWH+YwsWw="
      },
      "public": {
        "type": "Buffer",
        "data": "RmrYWoQ6hwfXS8+iXTeo5trVnrix5lb/JSh1xQ5oVjk="
      }
    },
    "signedPreKey": {
      "keyPair": {
        "private": {
          "type": "Buffer",
          "data": "2DUrNq0+f8Y6LrBa97UVzNRvepNaS0XCKkukuTEPpU4="
        },
        "public": {
          "type": "Buffer",
          "data": "sE9nluJNA91pC5Dg8QjYDqclXrZHpW+6C8rr7qHh8AY="
        }
      },
      "signature": {
        "type": "Buffer",
        "data": "paP2uUg8JUAvEzduQZbbKuznlzlGhrAINTIH0whFDrA2lei5zMS7dEM/cnqs7EW2xUE54IdsFkNhFFemjdu5iw=="
      },
      "keyId": 1
    },
    "registrationId": 38,
    "advSecretKey": "PvCJxtvfznyYk3KW7G5f104xYR8vMRDNtcVqW81HlE8=",
    "processedHistoryMessages": [
      {
        "key": {
          "remoteJid": "6281802826208@s.whatsapp.net",
          "fromMe": true,
          "id": "3DFFE45002225DA03C3C6C147B81DD9C"
        },
        "messageTimestamp": 1683310853
      },
      {
        "key": {
          "remoteJid": "6281802826208@s.whatsapp.net",
          "fromMe": true,
          "id": "CADE18905793647B541A3EA6286D0B48"
        },
        "messageTimestamp": 1683310853
      },
      {
        "key": {
          "remoteJid": "6281802826208@s.whatsapp.net",
          "fromMe": true,
          "id": "FB5367BED04A5BB111F4854074038F84"
        },
        "messageTimestamp": 1683310870
      }
    ],
    "nextPreKeyId": 31,
    "firstUnuploadedPreKeyId": 31,
    "accountSyncCounter": 1,
    "accountSettings": {
      "unarchiveChats": false
    },
    "account": {
      "details": "CNrYm5MGEP+R1aIGGAI=",
      "accountSignatureKey": "XByuNVHj+CICesSFlVMp9w0pfJnOadoBPJi+2PgW3CQ=",
      "accountSignature": "xTXBafsSgizzvjUTHUys06dHsXbxnFuVb0rAgjeF4avBAptHbZbf71pn2G5moxFzv81UGEpwIAij2bfJKY5BAg==",
      "deviceSignature": "tdJ6JibRn48yxoop7n3VNvS3uY8xMqEaqb5zIJfzVmsQ/9OcjTi6EGwwk297S0+e/S+5DOF2InPBp/oDaGkjjQ=="
    },
    "me": {
      "id": "6281802826208:7@s.whatsapp.net",
      "name": "Mama*Abi*AnnasYA*.....🥰😍😘",
      "jid": "6281802826208@s.whatsapp.net"
    },
    "signalIdentities": [
      {
        "identifier": {
          "name": "6281802826208:7@s.whatsapp.net",
          "deviceId": 0
        },
        "identifierKey": {
          "type": "Buffer",
          "data": "BVwcrjVR4/giAnrEhZVTKfcNKXyZzmnaATyYvtj4Ftwk"
        }
      }
    ],
    "platform": "android",
    "lastAccountSyncTimestamp": 1683310850,
    "myAppStateKeyId": "AAAAAAyy"
  },
  "keys": {
    "preKeys": {
      "1": {
        "private": {
          "type": "Buffer",
          "data": "GHxJXDvIZ/xDOdhuvV68pP8b2qIGDqn9+JMvtyD9/Eg="
        },
        "public": {
          "type": "Buffer",
          "data": "Y2AxiNCnkD4oWtSUHhdWfcpg4vnoxr22HZ8J0hjHsW0="
        }
      },
      "2": {
        "private": {
          "type": "Buffer",
          "data": "IDQIMf6XGE3y6xNYNA6KTG/JcpsGF/rhiYEa4PhqSmE="
        },
        "public": {
          "type": "Buffer",
          "data": "pwIe+ENhj1l2AoNs+0wnWoKK75rNIUXjJxt4lNJq1Ts="
        }
      },
      "3": {
        "private": {
          "type": "Buffer",
          "data": "aBtmDa4ZUc0Fpl/hhSa2MbE5e1isMdcL4O05p2nT+2s="
        },
        "public": {
          "type": "Buffer",
          "data": "JnWZHkTlx1IrKTLjrLg6CXmYLZblAY5D+uOTbKZOwHc="
        }
      },
      "4": {
        "private": {
          "type": "Buffer",
          "data": "aIbcxUQ6tkw1Ioz2aN+0pPm44rJENADCmhysSW8ksW8="
        },
        "public": {
          "type": "Buffer",
          "data": "8mS9DhxZlcn+cJdF79dGtp3QhYeM4zaSY2KpVx6wDXM="
        }
      },
      "5": {
        "private": {
          "type": "Buffer",
          "data": "AKSZwlfCB4xTFK8DdT+sLg83A93ZttEs/Ai1d+23PEs="
        },
        "public": {
          "type": "Buffer",
          "data": "Q9P7XOdWXxeogySpUX42xTjDV0VxLIjvhAmi+ATJoFU="
        }
      },
      "6": {
        "private": {
          "type": "Buffer",
          "data": "cHxIM6jmHrTJrB5fMDbHQbwFOjnVZPQM2EOgYA5p1ns="
        },
        "public": {
          "type": "Buffer",
          "data": "P3HhR/nqo63S7vbhiBFpxEI1nuoSpn+iTzTjpwKPTAU="
        }
      },
      "7": {
        "private": {
          "type": "Buffer",
          "data": "aHHjhF/fFQRa3LSodnBAdoJ8arSQt9yycmEc2BC/SU0="
        },
        "public": {
          "type": "Buffer",
          "data": "Iv5MuZyVDPC767EzqzoT3cFcp6nKcpKbdKyKhlUGzmY="
        }
      },
      "8": {
        "private": {
          "type": "Buffer",
          "data": "qCVJS3Dyp4y27EfkeCkUWfmltZzKh797rd7xF96S01Y="
        },
        "public": {
          "type": "Buffer",
          "data": "SAAQjXnfvzhMAoFR/PofgVgZJO21jmPjjtPAIJZByBw="
        }
      },
      "9": {
        "private": {
          "type": "Buffer",
          "data": "oCKWYd0UQzC1NBpUtmMJ43iPo8Pim1rg69zTCd+/9UM="
        },
        "public": {
          "type": "Buffer",
          "data": "ye+CF+xgIQJhp3zlFgXkODOWH4kBpoJ1B2YmEltJAHE="
        }
      },
      "10": {
        "private": {
          "type": "Buffer",
          "data": "mBhBLcT90cD3XmOYQMDz9zm62TIsFDcHDuRQWpl6uFo="
        },
        "public": {
          "type": "Buffer",
          "data": "ZSttUVlgBwLFmDH8bMW8B11OtqPc3ch247T8Z8BPTF4="
        }
      },
      "11": {
        "private": {
          "type": "Buffer",
          "data": "oLHi961OedCLaU5xWZk15S5vylRNtXuuz6DhHRi0gnc="
        },
        "public": {
          "type": "Buffer",
          "data": "2XViDmirRj+asPED4dfUa1aSPDGF/T6A0wFdhHT12yQ="
        }
      },
      "12": null,
      "13": {
        "private": {
          "type": "Buffer",
          "data": "cOXxp8d+fWH641tb4oYzsR7ctLUzFxhQiY8aotNdbWM="
        },
        "public": {
          "type": "Buffer",
          "data": "Aix6/420Y30bPb/jOTuIt6N7YJa7aphcrhI/q58mfWQ="
        }
      },
      "14": {
        "private": {
          "type": "Buffer",
          "data": "GLaZKB2HvRa9kMMNKBfL9Mfvu04PWVyFTpvdT20LX1c="
        },
        "public": {
          "type": "Buffer",
          "data": "BdlX+mJ1v2ywHalizMg1xVE0buP3A4Mvj5wjIcM/hQ4="
        }
      },
      "15": null,
      "16": {
        "private": {
          "type": "Buffer",
          "data": "qEDGH8FbbFrsL2+Q/sFQnb2aIyG2OJWmeHn+V4mO2nY="
        },
        "public": {
          "type": "Buffer",
          "data": "U21q99KZaasRyT/c0ZvpzuN4tXcaQA4dULqD7goZllU="
        }
      },
      "17": {
        "private": {
          "type": "Buffer",
          "data": "4J2zdikNnNdO5aYi6sd0RXoeoqf+pe/riuGoIe+YBkM="
        },
        "public": {
          "type": "Buffer",
          "data": "iN1fB2/rwg/ujGWQOHfulgMisrDz9tB/pko6BvR/jEM="
        }
      },
      "18": {
        "private": {
          "type": "Buffer",
          "data": "sAj3nQHMh/aRIZIXQIq5IgnUnuAW8t8xmv5WoF36TFU="
        },
        "public": {
          "type": "Buffer",
          "data": "+tGxJsy+D28wCkc9HwRYPma4xroGK3qylnUjJCW68xk="
        }
      },
      "19": {
        "private": {
          "type": "Buffer",
          "data": "uHxoOf56Qd4gXjH65ORobY1sOdlBHws3OpWXEMcjz3k="
        },
        "public": {
          "type": "Buffer",
          "data": "NOBcnzt/y6ESx/y9dLf7CNWc3odLRwhVvR4cPT8huhk="
        }
      },
      "20": {
        "private": {
          "type": "Buffer",
          "data": "sI326Od325v9IaU7pSLq/tvZwdO5KT1E/XuzkLd5cn8="
        },
        "public": {
          "type": "Buffer",
          "data": "U0t6zBszCzRP1lNiK//Djwih1JJcSq1Yz4RzxDF0bRI="
        }
      },
      "21": {
        "private": {
          "type": "Buffer",
          "data": "sLoUbpGsXHzMjRCRncNqv4fSmp5yBR7QrpzscLMm+1c="
        },
        "public": {
          "type": "Buffer",
          "data": "YY75V+mwAkaMTfdNi+YbA15OMeCHv2ye/gL5FigG0FA="
        }
      },
      "22": {
        "private": {
          "type": "Buffer",
          "data": "SElbj7p6bUXnK4GYQoN4L1JO4EHetoq+nGZpgrH/BVY="
        },
        "public": {
          "type": "Buffer",
          "data": "7Z/VLWHSDMa3TeVJnoIS+PACVC6nwiXxhQXXBRPt3Tw="
        }
      },
      "23": {
        "private": {
          "type": "Buffer",
          "data": "aBdEaZuq4vQ9YcIds+45jmYY59Ikq9k9r7wvVG5xs2w="
        },
        "public": {
          "type": "Buffer",
          "data": "zM7UIRfqlZFSGlf/wtzSZfu430Jsb3blcK6hQ9rhgAs="
        }
      },
      "24": {
        "private": {
          "type": "Buffer",
          "data": "mPuQ30ecMqCpvE/591lPWy24bfJ19vsfR7lijfccFFM="
        },
        "public": {
          "type": "Buffer",
          "data": "Skvyqd++6ApN0CpgDfnMEYGdpSJmO8JJpx+oKFP6+B0="
        }
      },
      "25": {
        "private": {
          "type": "Buffer",
          "data": "+LHZ4lygmq+WJNXWsttrKXKdNKZ5msJ0ubJ8Qlm7sHk="
        },
        "public": {
          "type": "Buffer",
          "data": "FUAAM/paV5GTeaUK8Vs9fUYsGF/Yj259vA0Ugfe5bFE="
        }
      },
      "26": {
        "private": {
          "type": "Buffer",
          "data": "eHaTfgIyfHUwe8eLEA96Eoo2VF/75O2DLia+LStLpEI="
        },
        "public": {
          "type": "Buffer",
          "data": "kr7vhgiS5MHJEZPp2pKoBddSTNBPRiuGPBGSYmRlQ2Y="
        }
      },
      "27": {
        "private": {
          "type": "Buffer",
          "data": "CH3h36pNdDC/PkgGmjzz+9bLPaUmgq84Zr7pVGvlpm0="
        },
        "public": {
          "type": "Buffer",
          "data": "cvLeSXyY3rdyDZmdrT0EfuhfgnLTfOuxFoUFq8ogEyc="
        }
      },
      "28": {
        "private": {
          "type": "Buffer",
          "data": "iFOF9as6APUNvShGf1RJ7jWjcrUkZ2C8bIv5PHkR1XA="
        },
        "public": {
          "type": "Buffer",
          "data": "K6m7JlAlgSzP1jtoFVxYFmvGAJ8tUNOCkIXKwgN+/XM="
        }
      },
      "29": {
        "private": {
          "type": "Buffer",
          "data": "iE6xx46iFUdn0192lqHCuJoaTaNJtncEz0fN73d8iUk="
        },
        "public": {
          "type": "Buffer",
          "data": "2ETEHbfbd7JjPRL9Hb40fKuJbcp/dAckKsjAeTaHdDU="
        }
      },
      "30": {
        "private": {
          "type": "Buffer",
          "data": "kKITPeZfnyiHIg04ZywW4ES3+HxaACDzDQ4+M0zJcU4="
        },
        "public": {
          "type": "Buffer",
          "data": "5PILvdjnpYC+gb2Ynu3EQgSSJIwDFGG33jl72WiQlHo="
        }
      }
    },
    "sessions": {
      "6281802826208.0": {
        "_sessions": {
          "BX2ogG43Yo90ncGndPvvSB7Wtt86wzx7vku2+g0VUhYd": {
            "registrationId": 1206600707,
            "currentRatchet": {
              "ephemeralKeyPair": {
                "pubKey": "Bf+nWGYqej5oIVsSXWTinB4KaVI41kg4AWRS8912DyRo",
                "privKey": "8NGydjwZIoWlTBV5gcQ/Gdf2ASOq0dHCXf3kr6o4hXA="
              },
              "lastRemoteEphemeralKey": "BctoFKDxM/bW4vXWWU6mQrKegYud+933TL+et2WCswZ8",
              "previousCounter": 0,
              "rootKey": "pQCAwqL6buuCF95/tRSk8jN4HHNB/1e+jlS02IKO3R4="
            },
            "indexInfo": {
              "baseKey": "BX2ogG43Yo90ncGndPvvSB7Wtt86wzx7vku2+g0VUhYd",
              "baseKeyType": 2,
              "closed": -1,
              "used": 1683310851778,
              "created": 1683310851778,
              "remoteIdentityKey": "BVwcrjVR4/giAnrEhZVTKfcNKXyZzmnaATyYvtj4Ftwk"
            },
            "_chains": {
              "BctoFKDxM/bW4vXWWU6mQrKegYud+933TL+et2WCswZ8": {
                "chainKey": {
                  "counter": 6,
                  "key": "GSSLa0y7PwtuNOpgX1nRAUiHZQi04nyDuIAR2/R0CEg="
                },
                "chainType": 2,
                "messageKeys": {}
              },
              "Bf+nWGYqej5oIVsSXWTinB4KaVI41kg4AWRS8912DyRo": {
                "chainKey": {
                  "counter": -1,
                  "key": "31+wbo0KeID3y+xC+epmkGXJL/Ym3fLDxmQOVLPxit0="
                },
                "chainType": 1,
                "messageKeys": {}
              }
            }
          }
        },
        "version": "v1"
      },
      "6288232154376.0": {
        "_sessions": {
          "Befy+A9dZVjQwPZofoGWv3G9DwE55i6xFZrFNjBCRxcx": {
            "registrationId": 263387900,
            "currentRatchet": {
              "ephemeralKeyPair": {
                "pubKey": "BV92rh+exBKAAILGxtflJEqnyqHvn8mlxAlBUfyxxVgl",
                "privKey": "6NxVdwknfkwgZmRSbUxkHVdbU9/TeTWqGcJml5Ae92o="
              },
              "lastRemoteEphemeralKey": "BW2+Z6yDtkwBBm/pk3UVaTYgqtqO6qDGIu8qVGvszf5h",
              "previousCounter": 0,
              "rootKey": "iXJn+cyb7NgV1ISpl7y3YWvOFfXxj7xNgEyk8SuJ36c="
            },
            "indexInfo": {
              "baseKey": "Befy+A9dZVjQwPZofoGWv3G9DwE55i6xFZrFNjBCRxcx",
              "baseKeyType": 2,
              "closed": -1,
              "used": 1683310872999,
              "created": 1683310872999,
              "remoteIdentityKey": "BY32YaSmIzGJDVRcA7CbkgIj+AS/ZJvvlLr7epN4PEJP"
            },
            "_chains": {
              "BW2+Z6yDtkwBBm/pk3UVaTYgqtqO6qDGIu8qVGvszf5h": {
                "chainKey": {
                  "counter": 0,
                  "key": "7CxH+DYJtjcMbqV7Z9pjQ+VWClyy/kLsF3l8Lz7Alz4="
                },
                "chainType": 2,
                "messageKeys": {}
              },
              "BV92rh+exBKAAILGxtflJEqnyqHvn8mlxAlBUfyxxVgl": {
                "chainKey": {
                  "counter": -1,
                  "key": "JpNGh895vtoJj6a7ZWE2HxP3MQ3P6AUhxSJtnmO436U="
                },
                "chainType": 1,
                "messageKeys": {}
              }
            }
          }
        },
        "version": "v1"
      }
    },
    "appStateSyncKeys": {
      "AAAAAAyy": {
        "keyData": "DwnbV1DUihld9qw1/LjHwd9apJoycLjuSd1KVfola0Q=",
        "fingerprint": {
          "rawId": 1650912346,
          "currentIndex": 1,
          "deviceIndexes": [
            0,
            1
          ]
        },
        "timestamp": "1681135286825"
      }
    },
    "appStateVersions": {
      "regular": {
        "version": 1,
        "hash": {
          "type": "Buffer",
          "data": "y8GvzjepXx2YwBiktxOOdIB6cM2xrfMeqKiif0jqWnmm5HspYp1Bu8hh2Wo/llude+y2RMWM5HSCu5HTQkjifTNp0Lb/eVZKqox/n+uZZjX9Tc30TqexCzHDQ492oriVgH+26/fCYQnSYxbxXaf7ULMib+CDWe+8SSsYcmcrUvA="
        },
        "indexValueMap": {
          "NB7M/WSZEZJfQwiIBZXJ1CjWtB5SJVJDdDV2KsbLrSk=": {
            "valueMac": {
              "type": "Buffer",
              "data": "0QqUmWGiooVlhLpOXBeIP14GdseG8Sa1v8WtIjFQ6Do="
            }
          }
        }
      },
      "critical_unblock_low": {
        "version": 31,
        "hash": {
          "type": "Buffer",
          "data": "vHacRnIZi0E37k1iq9fHkNIef74m9SOwAbYQX0Uha0kiIPMdbbVbhnSUCj8tkd4mMIWQ/Yei7yZaTL76xYSoREsU3Xk5qAbLjAGABi2+I3IaBEPv+Pkm+mkqja/0QGgVXOPicDK+YTL+gBZgKOU0YITldqPpk6xJybO8EzAbz8E="
        },
        "indexValueMap": {
          "Anj0O1jQZhVWnvfqXaWSM/GQ0ACR2wpirDs2Bc6G/n4=": {
            "valueMac": {
              "type": "Buffer",
              "data": "V8LPNpjvfpLO7TIryCYeCtW2TfChNNBEK8bkYFonYFI="
            }
          },
          "A8g6/f9poOX1AUiH52l0FnAw4SFpMhQpteGEYp9viWg=": {
            "valueMac": {
              "type": "Buffer",
              "data": "TTbXz0nEVxve4vE89uWy68G9RRaSMcK5mTTxZqA+GqA="
            }
          },
          "BsQQhP4N4aLyLw4QNUTxW0Jkg8YaSvVBGhcfJrH7svg=": {
            "valueMac": {
              "type": "Buffer",
              "data": "Xaqoj5onsJSJRm3024q9PVmDAmsV0WoN+9RtZ2lTpeY="
            }
          },
          "CCD6K2fy54hXdW2EoE6NVLtSDk0v3ilEx2n8mDhVf3s=": {
            "valueMac": {
              "type": "Buffer",
              "data": "goSseFguxjTiGtL9LHxXzkBqX8YcFvDjdsRjpLZ9f4Q="
            }
          },
          "C2O1HG2YM8SONuKeoZUNGAKdqdrJO0l4z8vBXKFoKkA=": {
            "valueMac": {
              "type": "Buffer",
              "data": "eaorbfLa50QArdm9uwqXMLRM4MUw06HAk8RyxICRJqU="
            }
          },
          "C5kcdDZA3uSfwTjsJAADPYZfaLAijGf5jB0vfhCrIKw=": {
            "valueMac": {
              "type": "Buffer",
              "data": "yZ25EMxn6l0HmUUAm92TewRhpmWzJVzWX/cwJVfS5k0="
            }
          },
          "DWRXXNVhWhkSNPl44IP8L+I2/QxgcN7HVvIO/A4BPgI=": {
            "valueMac": {
              "type": "Buffer",
              "data": "yq6vfPwxtB1Ka6MjHKnFipZ1Iw1vVqL11VysurAqPCk="
            }
          },
          "DaLneGYqMl6TNc823yKxZDh7v0iCdd+0n4oDDHbQeIU=": {
            "valueMac": {
              "type": "Buffer",
              "data": "0jxW2L9P02bTndP2eZ/rWn+VdE777huNrJDZnI1nmKc="
            }
          },
          "DpGRqQ4gXiTIJLd62gHxOhphcKYKWz5ufmhWW6oZvOo=": {
            "valueMac": {
              "type": "Buffer",
              "data": "n5tHXopdYQBJGh0Yzdkh6lgBlFnbwyszUj1g1Ie0yME="
            }
          },
          "EAqvS11YU4LmQGr+ElEaeaRS7LN9vUUUptz0Y1FGfB0=": {
            "valueMac": {
              "type": "Buffer",
              "data": "jrus9+R5Kyk+pPpVPUBo33kq/uaisg6mM15+cdtv2y4="
            }
          },
          "EIUDW1cxfW3a4ThJB/aXpJ+oGQ2KVBY1woigxMheAEw=": {
            "valueMac": {
              "type": "Buffer",
              "data": "kkB/s9HUojMM/VU0wc7FOpBEYMlNtCqIy7V0y0lCuLI="
            }
          },
          "ETHWZVHyLvAFQ8ir1QHcdkPlxz7cHewFPVy/VLvUKkM=": {
            "valueMac": {
              "type": "Buffer",
              "data": "R0IsHYHeWaROm1S1c6GBD6KmqnjKlHH6YsML9hQB2KI="
            }
          },
          "EzuNz4+FY0XqPTYoxEkhCa6HHy2DURcTE1rlQcMtBWk=": {
            "valueMac": {
              "type": "Buffer",
              "data": "Hm2E2L0VtzPKy9wKU7LCLvbSVALGZKN0H00MTX+hY3A="
            }
          },
          "E5voTuDI5BpszaKQsYbOgnGgox17mUc9lfKhnhjq38Q=": {
            "valueMac": {
              "type": "Buffer",
              "data": "rRCRDX4WjBKRc9uC755B/xd/e/WRV5I476JuKbHm7Vg="
            }
          },
          "GLHhk8ghuBP8UXnQt7jCGTYkJ4ihJDofdYJK/k9EEUk=": {
            "valueMac": {
              "type": "Buffer",
              "data": "wSkTasxAnN0H7aN4Y0QA1eL77wG4ki4XjT4m76yVuUg="
            }
          },
          "Gt889S0eIF/iGbj6JT2/F2ctuz81PLjVYgUvITNWW5E=": {
            "valueMac": {
              "type": "Buffer",
              "data": "LTOH2i+XclAWWB+ZgxreDpHsUaA9YthFU2grdFj60TQ="
            }
          },
          "JSNqLv/kV3EI+hM0NSMqToPlxjhWNyeisvQ7U2drPKg=": {
            "valueMac": {
              "type": "Buffer",
              "data": "J+cKBDMeQwVsmdXB/Lmx63hx1tFyfQ+lMLVL1SMDMRY="
            }
          },
          "LZxRQRyK2c/YPAMYWAHD6Ad896Jbu/cpOwj1I78gS0Y=": {
            "valueMac": {
              "type": "Buffer",
              "data": "2A1TNGKAUMcG9fHDgwZASDQUzwRB9XHBLtI73z0vXEA="
            }
          },
          "Lc1+H+IfaT9CWEgJahvc1fMvbdMM/AgvtBrxlFviM3E=": {
            "valueMac": {
              "type": "Buffer",
              "data": "aTAAIMGN+SmeVAXzqYR/F1nIUcK57QXZdZd8fy2nm5o="
            }
          },
          "LrodCimNAwd+jMeV0SGtXqXKzVQpcfTD5Sx9BMy0pHg=": {
            "valueMac": {
              "type": "Buffer",
              "data": "Je1OPqe3CSYyOJwpvKqB9Yoi9vBAL9qPlZUVLM1bprc="
            }
          },
          "MNTHqTcOqSBR4ue44pOqzjY40g6QHpwWPskIgCxKOEY=": {
            "valueMac": {
              "type": "Buffer",
              "data": "45ftUtiWQWylANbRZ1HCSqwDPIOi9yr3BUb87h4raXY="
            }
          },
          "OLKq6AH3Ui+ltdqtuhgKo87pBNJRyXpF2yCJRRSO2hk=": {
            "valueMac": {
              "type": "Buffer",
              "data": "WqqWKgBdljMg6SXyOWq4EMZTbPbGf7rW36Y7qWI5ksA="
            }
          },
          "O2bWx2zinNucz7J4Y1gRp6qegDSJLGfN2qoK7YyGoKY=": {
            "valueMac": {
              "type": "Buffer",
              "data": "ZS9xWYlsOf2HqqN/BasH8xZJ68aBKj3PYMPUuYVCASs="
            }
          },
          "O6YsOvbzhSiON3fzsEXFF1RH7NCuP0uYEoeJ+FruRLg=": {
            "valueMac": {
              "type": "Buffer",
              "data": "uEM1e09XL0b+kPakh8V9P8fGLXdqEFn+T8oC/RkJHnE="
            }
          },
          "QmP5SDKxqPCrXcj0et9teX+RA0pcNAwBqnqRMdsutuA=": {
            "valueMac": {
              "type": "Buffer",
              "data": "jpBVrVvYS+/FEoqwNc8tQK1gXIkTj+7GWy4K/GYmt7E="
            }
          },
          "Ra/sP+0beG/sPdba3ugG7ujKOElZNBgPQizSYaKbNSs=": {
            "valueMac": {
              "type": "Buffer",
              "data": "JjfPCpM9YhkwWXN9yEJUbTKUOsCyY7rOWtfqanpRBKo="
            }
          },
          "SPrh0epqWuCLwWFPm1HfE3FBMJLMv2jpqkshZwGVdIk=": {
            "valueMac": {
              "type": "Buffer",
              "data": "XGPEufTABL+HL/z7Q0cP/OnnN8DOblHbKR83YYU8gXY="
            }
          },
          "T8YPlDgaRJnSuxSlknVFypvYKFxOxkOkmlxJvYvkTIA=": {
            "valueMac": {
              "type": "Buffer",
              "data": "IMiGk/ceoPxfhOgsPE0navjQJKUKMiY/xl/uKOjVWzs="
            }
          },
          "UzdtzbBFA7v1UNMxVqJvzav56kuPm/GO3obkHzO2QHk=": {
            "valueMac": {
              "type": "Buffer",
              "data": "/eVROEn5k5rp8gGkAkVriXB3VKv4JSFZZoJZ8yj6eKk="
            }
          },
          "VsqwC/qe5l42m2JVcQd/9YxFsUQYy+viQLcgstzfcMc=": {
            "valueMac": {
              "type": "Buffer",
              "data": "TebL/iRGiWg9vwCVFPD273cBrhXvyBk6GFPPXFvYQOs="
            }
          },
          "Zo3vjXUOjMinhdZxMIPermBXS73Hq6sh7rIxWlMLZ5I=": {
            "valueMac": {
              "type": "Buffer",
              "data": "Y/VsuITERcjrymorqAFyW718Fhi2K4CM6ecoFIy8978="
            }
          },
          "c0DJwvJtDeo1Sww+BVnU+oUT6JcZu+wI9sw6r5QgYVE=": {
            "valueMac": {
              "type": "Buffer",
              "data": "2iTGrh8r9psB0v4XIrw+sk4Ir9iqoobKX44aQuYP/2E="
            }
          },
          "dJYACBtZpUkog5xRG4Mq1rMp3OZj7D9BNXgjAG2DexU=": {
            "valueMac": {
              "type": "Buffer",
              "data": "fEUSxwnsjUeEAM5A54gqTtPIf6iKDcfTV2hptlTZWqY="
            }
          },
          "ehzwEMhaLuSK8Zt7iR0PW3NYFZQ+kX+K6lHZMN2TUV4=": {
            "valueMac": {
              "type": "Buffer",
              "data": "DrEfEN4/Thx1APsBrZ1Wp1nb2TFQB48Xn0CGGKxHq+o="
            }
          },
          "h+6eK0/JK/z+rwPnuuwrX294X1sJ9v/mKa/fa9i9tR0=": {
            "valueMac": {
              "type": "Buffer",
              "data": "AesvlChYpObVx4+1twU+kvolpFikWIHe3GS4ZOKct/E="
            }
          },
          "jF1b156lEnoiEFxdsxLtsqXHeGg1+nWn1pZzeWi+/ZA=": {
            "valueMac": {
              "type": "Buffer",
              "data": "xzQOMw/hsenTNVvV5Fy0j0o0UnRNkoilMyZwvqGm+Bs="
            }
          },
          "lfIZBZKUaKI8BFKsyoLnSswcu1TdvQfwjFplW8z/H/0=": {
            "valueMac": {
              "type": "Buffer",
              "data": "dbdp++iYz20v7sYyudvu0otWIWY/yjr9lv250GI1lKc="
            }
          },
          "mRILmiJ4YTyAa1w1p/Hbk1hs9sM1dOzE9UjN0XrsIac=": {
            "valueMac": {
              "type": "Buffer",
              "data": "4ATReb+Du/GVN8ZiC4N0FsNyDUX4yiIgnGh3RUgT3W0="
            }
          },
          "nqE3NRa7SMm0/Ug3NvqJtDAml80nJg29GrhAicRKjC8=": {
            "valueMac": {
              "type": "Buffer",
              "data": "7zxAhWU7vtSKKPadaIgK/gi9s5/lgGZJvTYWgZPhovU="
            }
          },
          "oNh41l+/lPWyiqoLoj3tjuLjmTFYsJkC839ExFGcGyk=": {
            "valueMac": {
              "type": "Buffer",
              "data": "t/xFVcG+j4FGfalNR2PfsO0PjDy1LE2RRPDerApo6K8="
            }
          },
          "olmunjGWuPcMSC2629cNNProVTfrMyrpFyv5ah0TVPI=": {
            "valueMac": {
              "type": "Buffer",
              "data": "KvWM0AaJwHoUVn6jUU1KIiGi5z5jsdjP92uTUfTplkU="
            }
          },
          "o6oIbABVAVB1KEnvmCjD+NmWcIUkBTpGF1OOXrskOoQ=": {
            "valueMac": {
              "type": "Buffer",
              "data": "6indzYXcYarBDWQzCri2I2DAeOOC6LKB/OFjFodkL+A="
            }
          },
          "o9R8+Y+FwfhEM3UaiTTcfKq0QDRXCR3AkW0aJuiLLfQ=": {
            "valueMac": {
              "type": "Buffer",
              "data": "ndP0PlB/Ow4XbC2/D9e7yN9CcphFUIRmXxHZyQWy0fE="
            }
          },
          "p4+VPuGSixoUgdVomZ6u5kVPTLFL/Yw4fkVqgb39eKw=": {
            "valueMac": {
              "type": "Buffer",
              "data": "Lp9oewlKapvnYgeEWSeWwfW7xd5DCDGTKovUebV6NnQ="
            }
          },
          "qx8MGkC9oBaCJQwDkCQrLKwhXpu+qKjewezqbXjLPzc=": {
            "valueMac": {
              "type": "Buffer",
              "data": "vZ171JDkyPzNV3cvVIEL/VvcijHNPIqQbnJQd8tG+VI="
            }
          },
          "rSL3zUQqv5OOWgYEMlMThMD55rwUUDCeb2jgaU3XOxA=": {
            "valueMac": {
              "type": "Buffer",
              "data": "4hWN7XhGKrd/6hX8BDLoepTl5NjTYQtbNfpBO2dZHtA="
            }
          },
          "sIYx/p1WVYQ0aWpYKpls5xNtmQtC2HIGFd3n9WU89MI=": {
            "valueMac": {
              "type": "Buffer",
              "data": "tJ+Nz1pOgo1tkFVFlXxnH/2DZ5RPP1NeuuFJQ3phBs4="
            }
          },
          "sY3EIh2X50TbgWI0fNyUXRJ5UaIikRi0aZHFGJbIbiE=": {
            "valueMac": {
              "type": "Buffer",
              "data": "J8vGNa1sKcEuf/5NmSqrMS+WugcksQiAVd7P5u8oF7I="
            }
          },
          "t1PLtMtxoGceZwFSYEZwrr3VdZltxBhSsZPB4v1mRnk=": {
            "valueMac": {
              "type": "Buffer",
              "data": "odhlBbbrv0GZFlM4dqk8XD8SO9FF4BNCHt1ZFfvjWic="
            }
          },
          "vOio304vnja0QETll8UJyeTc38tepkW3nRAHUP9E/HA=": {
            "valueMac": {
              "type": "Buffer",
              "data": "lVzlRQuybiFx20C7Opujc+9Js19Fvf5Je40oJE+2ZFg="
            }
          },
          "w9Cnay1klgMm7hyGMKqFZEzWtCXBbQGqUWwTW/VIDKA=": {
            "valueMac": {
              "type": "Buffer",
              "data": "sZLLqEXNjtI5km+c8MN+7TwLq54XybsqP3OzAAhY/PA="
            }
          },
          "x3zNDDb/HdAoChBrt/+8ZahIAGbcc7UOi1WfC+ELIWs=": {
            "valueMac": {
              "type": "Buffer",
              "data": "8YgzjWxyqCFBtL5E/A3yEgAhqCvDKGfbyKHNa+65yR0="
            }
          },
          "yCVOS7yBCm9/4u0Dvn7ofs7OKA7Xb367ybFK0R0Z7ok=": {
            "valueMac": {
              "type": "Buffer",
              "data": "DgnX9uC14mAV+/o/mzzEjzbnYWw3aalC1oR3vBdYLto="
            }
          },
          "zCdmlpA6M8DWZSObxM3yPJKAUPeJYswZZN+PSFnPRY0=": {
            "valueMac": {
              "type": "Buffer",
              "data": "ikFxl1IB784O30VjVffjgWHpyVWn9kAceNU4x9z6cio="
            }
          },
          "ztrR6KnVqQkCPdfdB/xXKMFoW6e8bI4Iepm7O2XATi8=": {
            "valueMac": {
              "type": "Buffer",
              "data": "WLoKGX1yTuk74wEl2REmJZ4wdL+DkprVQZ3Etm3eR5I="
            }
          },
          "1aR2fk3Dpjj/+ADSClULC1cB2IBb23i2isjiuFk4wP0=": {
            "valueMac": {
              "type": "Buffer",
              "data": "f9jWEGgh7VMJTQ2R36T014qMv2M3/9VFz1LIvLnpYJU="
            }
          },
          "2T4vIpMH9zJxF2gPzNH8wg+FpIrkDYrXd/eLA6KTW3g=": {
            "valueMac": {
              "type": "Buffer",
              "data": "ooGazDLFpGfAtOHMsdq7k4Fyef+YIx//fH//m5AjGTE="
            }
          },
          "2tdMsTg3A7I3QrqLksMIb8uMzLYDC6UG1DXp25Jcr0U=": {
            "valueMac": {
              "type": "Buffer",
              "data": "/GT2Cyb21c1wif4n/0lQvjGNOC+F+FBK5NAO+0waFGQ="
            }
          },
          "273RJ8IzNxpJ3G7jMR1qtbSE6M/zX+hZQX26Nj2nt+0=": {
            "valueMac": {
              "type": "Buffer",
              "data": "AdLi9F8dOfwu4LgBNWusuCXyUqH6WsbxN8ppW37VUGQ="
            }
          },
          "3FnPeZ9GfNDAKrS1CU8gfisoFn68qCBzubV9V+sc+lw=": {
            "valueMac": {
              "type": "Buffer",
              "data": "+PxJofeYT9Fl68lf8ztHCZcHrLRvAgK0xnoXrcnXft0="
            }
          },
          "3jIb793T5FjfHrdLMuDg9Ndp5M8Mzsi4JHnZZVDcBPo=": {
            "valueMac": {
              "type": "Buffer",
              "data": "o+IbvIbiVD+eubQK4bpQ96AScg/WLMcjGkVmErAXLlQ="
            }
          },
          "4XGAGQpxJ4Ub2dAgigskvCMIsqeoCKIOwR7gt8WpT3E=": {
            "valueMac": {
              "type": "Buffer",
              "data": "06qaKC/qNKelGNCuPD/aUH5PYPndu/unuvFI7tUe5F0="
            }
          },
          "6FHoOQRfblul0aJPmwncGft+ymEyzkXhc66qhbcjEKw=": {
            "valueMac": {
              "type": "Buffer",
              "data": "/310YnrRUMP/oK/g/KIgGjdwi+iEP4nupMmHC/+Fu1Q="
            }
          },
          "6bWY1HXzcen/LdsvBxAPcskZOr6KErrBePadLCO4Zxk=": {
            "valueMac": {
              "type": "Buffer",
              "data": "QVDhqFJhsjEZZY3m3E+1/yOejxNX3e7rSmoYzTwMQWE="
            }
          },
          "7Tt2s1vRUR938CkY2UHB0cwN3dRAFqo3PZJvSySYlNw=": {
            "valueMac": {
              "type": "Buffer",
              "data": "9d+W8tsQo8a7O1AlLNFXMuotSOyDiiIeSXEdcVDhMdo="
            }
          },
          "8AHHR/GnIe9F2nSo+OMpx5EY94b/RtUHzzSGtkjxCKA=": {
            "valueMac": {
              "type": "Buffer",
              "data": "t667OEFECVLbOMmL4hTciuo4g2ie6iq9cP13GtkBNKw="
            }
          },
          "96u/JGMzA4JIXfy8lZxpnEjk5xxrsuYVprEexg5EiBk=": {
            "valueMac": {
              "type": "Buffer",
              "data": "ItqM/clrA+VORMQA4JK/hYlCaIxdt9oespEk2fNmTnc="
            }
          },
          "+CBfCIccTqdLTcJlu4eViNtW+1efYvqTI+KUGVgLHFw=": {
            "valueMac": {
              "type": "Buffer",
              "data": "7hbavTtIpkI6BuebaSL1bRCr173u18Lmsao8+2xg8qY="
            }
          },
          "/Qu+RfMAaC40riPnww7uG4POSwcKD0pLHPSZXUC0mpI=": {
            "valueMac": {
              "type": "Buffer",
              "data": "B5zdwvGHPwdyMvwXnCk0pK4sal8FVhjvqBplE86CkTY="
            }
          },
          "/zMw0XIsimP4uEJ1HKH5aVWepLx7fD+EycRCZlywitc=": {
            "valueMac": {
              "type": "Buffer",
              "data": "VSyC8ecaTuNiu1YdzJWFzreJ5QCHYdeDyI06J7MB8n0="
            }
          }
        }
      },
      "critical_block": {
        "version": 2,
        "hash": {
          "type": "Buffer",
          "data": "b+Y92wZb2P9L0qcob0G8xvqSHcyTXBhUDXPOg55TL3XjW/mq11rn/b+1TN5WJMDh+4rSs+hMCy0XSDRtM782M2e+/mAh16zezEQsfUG2OD37fPl89zoJ+Wt0ZcMsPUA/V/q1C5skwwBrqjOx14haBSagHJGjJyFLJWYurpi5SlI="
        },
        "indexValueMap": {
          "vOfUj9Rzt5kSNg6BpHiM5vLUOHgmXv9UZVKbjJDtrdg=": {
            "valueMac": {
              "type": "Buffer",
              "data": "h+APAE/sRqlewFdkAJhmsNCd83y0IUdzuhjEjsjeltE="
            }
          },
          "v3j3lsWakirRgEn9suudNPScOE4Y0NBI/V3pIgtV/QY=": {
            "valueMac": {
              "type": "Buffer",
              "data": "kv2XxPYCgPv6WZDe2wGa/YoEKb1doDjHNaHVlg1oB10="
            }
          },
          "Da1Vb8zrCwMJpb2GGHurVqIdQzAgiWLdNl9Zqx/epJQ=": {
            "valueMac": {
              "type": "Buffer",
              "data": "WXESF/waD2xzmfsiOHviXaqfEx7iyFZj6OAP4RDmXNo="
            }
          }
        }
      },
      "regular_low": {
        "version": 23,
        "hash": {
          "type": "Buffer",
          "data": "ihmYekRUHfpxIBCp0voNXy5juYaQrDomg+Xb8acn3HrHLX52zvyFKKff9QC5eFT5FZG+cPPhy4DVqz71OO+rPmS9wJ0a8yA5ZZTGRowvRatzdXzrhqIt/GpF8CH91ji/phH7jbvnPXYDtvZmYsI91MBdLjJDgSU31W20/nF94dw="
        },
        "indexValueMap": {
          "DgkLx71HvBZ/AmYIntIfllj9vPE8NMvj/v6cZhaq8Kg=": {
            "valueMac": {
              "type": "Buffer",
              "data": "Wyu0Rdhqol1H3lLR4fkkgrzBYH0CB25yPm6vyvbFW6g="
            }
          },
          "EBxgLy9v35dzXnc3MJ5oYaPMO4KSgBezoa44kZthJik=": {
            "valueMac": {
              "type": "Buffer",
              "data": "T3065PyH5jvCgRIkfTr8WInvpRVljXIW3j4h963mqZ4="
            }
          },
          "FzpmZR3dGpbc3flbF6OJEYDgR96CSwGhKF+T42kNvxA=": {
            "valueMac": {
              "type": "Buffer",
              "data": "jhyl8xfFaqHeK0ZDkDiF3xf2SI+WLS5juqeBredjX1k="
            }
          },
          "PjyXxhYZIgrjYd9fuOWtcjJgPi8V8aZV9AhnE1NN0SE=": {
            "valueMac": {
              "type": "Buffer",
              "data": "sYGxJdfQB5igYKlKnCfWctm+Hza5VTPvhX6QXaRY9o8="
            }
          },
          "U0cFoetxCAk5cCfdBO4C1PcAQg46SzDXEqcFIKGrI8c=": {
            "valueMac": {
              "type": "Buffer",
              "data": "2Eyj1YbMQtX3v8lXrXRBaJ6lOG4wn6oYuYrDdk8IUQ0="
            }
          },
          "VWItYUWEW/QgtYla9+zmpfouzdxMU1y4bjydLs6RuN8=": {
            "valueMac": {
              "type": "Buffer",
              "data": "NuMYffXKg3kuBqhg0Yaus5Bq1SnoVDhR/Ydl3w9vEcs="
            }
          },
          "Za1P8orQSrZYMwT7HDGamENCKAduS8qgw6Qs/BcClkg=": {
            "valueMac": {
              "type": "Buffer",
              "data": "dkRZFR1rCHXs1sK9/bYNNeGqZ73/lO135rM+VXKKthM="
            }
          },
          "gySTRZaPSIgNtyM0nYfbLY7Ll7nSKQYqtSMMiDZ4I18=": {
            "valueMac": {
              "type": "Buffer",
              "data": "sVVDiHb//9F/gRx9a+jPC8VjKCNARmX7/5KY7EfsUxs="
            }
          },
          "tZiao4ggcwRJ0NpSpwJVIj7b0OI/7Gj6+bxCw/R6DwM=": {
            "valueMac": {
              "type": "Buffer",
              "data": "MVQkwGBDVvpT9JtWeT24PI7HSCP/YPBpG30smQ+hyao="
            }
          },
          "6HanrqFLpJLIEhNZOFEV4RN/bF83zRIVRQgZgahK/bw=": {
            "valueMac": {
              "type": "Buffer",
              "data": "0q1OyYPg1MXNjX4lAWIECCzPYlcAX2wpyjYdqXEF9Y4="
            }
          }
        }
      },
      "regular_high": {
        "version": 69,
        "hash": {
          "type": "Buffer",
          "data": "qnVyL9dmlexA2GJcQWdKMubMAE3WJ25NBwdDcya4z20Lj9oC2rQFDyMFvmx2wgPEqG8s5QbUm0OySRrK2hlEujqlHyrhElL4DZgq9wtWg3l7uAGujyAVR7Ee6v53PQY2JNmFJMoTFRoBf3QqQuk9TCmMItTY/Q6UQndyE06SQ0o="
        },
        "indexValueMap": {
          "AgsVzLys+ZO2tbDeg9mbZ+foMYDYrpqiN3gbz3q+Gmg=": {
            "valueMac": {
              "type": "Buffer",
              "data": "kOKHbjQ4rKUkNSoY65aGRvaznL0byZx2nysoLZdQEN8="
            }
          },
          "Ameq/clNvsku3A2Ly4u7F5t0teshwqx99/zK011oPMQ=": {
            "valueMac": {
              "type": "Buffer",
              "data": "YvqaHa4MU4xKTb7YStRjxDza8ZUm6X6F8nqeamnvAa0="
            }
          },
          "AwWpA58zQ0hc8mFyp6pmWFR04n2tNCp2UsrggUEJmfY=": {
            "valueMac": {
              "type": "Buffer",
              "data": "ZfnbrlhlYg0mgF8lGHaR46XmMZASGSd3h9gAMu6rYho="
            }
          },
          "BKi/Dd44Jr8zX3EjSLlEUTDJ2RFW1i4QtrrNbnbDSOc=": {
            "valueMac": {
              "type": "Buffer",
              "data": "2lFkkCUGWbu3qSPdswGJBHMSeV8noklkgJl5x9cgrRc="
            }
          },
          "CWEAQeyBvLfh96ojnv5xe/2YeH3ddfY3H8FGVkgN1IQ=": {
            "valueMac": {
              "type": "Buffer",
              "data": "nLonE4xWrWe5JyIKNLOxm9fxJj/lEwhjF2rRTPM1N2U="
            }
          },
          "Cx82dFmN6iAAYFIXhdS2qpHEkKOqerWu8Y6+Qf1Hjmo=": {
            "valueMac": {
              "type": "Buffer",
              "data": "cdTkPgW5tSAP6BbsKpAwiIDD9ChYLerZIuTVwh4rTlo="
            }
          },
          "C9dlbWhcTwnepRJ9hq5teCHDfKFRDI2BBPhxSx3QyQo=": {
            "valueMac": {
              "type": "Buffer",
              "data": "xI0fGuTLLeCqI5MUv3wPvIHClpDpihlxa4RbrCE/7b4="
            }
          },
          "DEMGXRynTz17SWCjd649jE1FO7pD7J7SD98yCGm4M1U=": {
            "valueMac": {
              "type": "Buffer",
              "data": "rqV/KhK4IRNWSZpypfYGkui0n6V6J7ufc6jshzVrs4g="
            }
          },
          "DQ8598wIjvHU8ieyzhRWtSLrWCIaY1bJ/CqGqveM9eM=": {
            "valueMac": {
              "type": "Buffer",
              "data": "AAhRL9apBuKbZUfjyGjC59ZdG1MiEMlzNF1zXPjtjyQ="
            }
          },
          "DVa/upgEKqmb/wAreMV+qD7ZxB2n23u03kjYO57KpHs=": {
            "valueMac": {
              "type": "Buffer",
              "data": "TbfBqPP6HB6TMC8ceT1BBo1CTlW5Rcio9e/h/d2Acbs="
            }
          },
          "DWfaVjqh4tcKq+XGie06EvC+umSmt+CNYcw+WPCdnnE=": {
            "valueMac": {
              "type": "Buffer",
              "data": "VouSK5e7W5mWRGWXH1CtersPEP9WmBwBdkcceUHIUSk="
            }
          },
          "DYRiJGUbMUUrM6+YUpWlcJ+uXWXyfv3BkZRycb4AiLU=": {
            "valueMac": {
              "type": "Buffer",
              "data": "mo03VVR/rvJtjwr1U3pVWKWQ09vEuRV8bds92dMtky4="
            }
          },
          "D6jN1QZzmvgCgI2y0dr/dFgSCY/KLSAGUrJlhNVKr04=": {
            "valueMac": {
              "type": "Buffer",
              "data": "ty2LiCl5QRv8Y0swDkMOn/v+juezwePPosEbuj7xX9A="
            }
          },
          "FGhllGZI/YPyp/TCj1l2atl/e5VGfRlVZDWJApCZDGU=": {
            "valueMac": {
              "type": "Buffer",
              "data": "CtLAm3eJwyGNy4gwsDU98jiyfI69nShwP8X4d6723bw="
            }
          },
          "FRbbfQ9biKXtua2OxCCL5W8r/5ULm7y1bA4UpuBqUoY=": {
            "valueMac": {
              "type": "Buffer",
              "data": "zhxMeKTSQo3f839wh7nxLsTGelM+09tn0GNW1EnmwrE="
            }
          },
          "FV2XwIk2sycI7bU2L07qlGuVCVjhKNNz1nX6XczUryA=": {
            "valueMac": {
              "type": "Buffer",
              "data": "bfCbjNR3XoFtJxrG87nxqXqR3SmBOIJD7Q4ZyJSepaM="
            }
          },
          "HSc09i6Gx6WDFuJILlS/N2drveZPg+Q3h2suShoWShw=": {
            "valueMac": {
              "type": "Buffer",
              "data": "cQo17nyylWRI2yLthw2/0bL4BTIoiwbznviep5Mwey4="
            }
          },
          "HkZH7irzP2BDdY+fYl8/zDUJiib3b7mZ0kl0/Kpa0us=": {
            "valueMac": {
              "type": "Buffer",
              "data": "lSurl5O1RicC7edTwkcbWiOjNQv36pqFXUww0IalJbc="
            }
          },
          "HxjczhUHKSOw5pk4d9klowl9oYyuQ0snoHGwDEaijQw=": {
            "valueMac": {
              "type": "Buffer",
              "data": "ATFe6epmAf7r6pmxWUKNpAaSlerLkyxAD3Yz4p+Glbs="
            }
          },
          "IPlbvVEbey1B2SKjE3agbACYcxjOMtP4bfLibGJPC/8=": {
            "valueMac": {
              "type": "Buffer",
              "data": "VICUfehnXqGHepWd9m2FzcXwHvtq1rkgHGtBlrp5hew="
            }
          },
          "JLxX5xI/MPIpLFGcgWxoo9Nfar9NmPULxW1lCmiLvg0=": {
            "valueMac": {
              "type": "Buffer",
              "data": "QmQDkPf4OnbV2UcxSw8zCxKAjwUq6f1+EPIet/2aD7w="
            }
          },
          "Jko/hGKVSflBjSBV5GKlyRPfMENi96kavvQXSlA+5B8=": {
            "valueMac": {
              "type": "Buffer",
              "data": "dO822PR7cybol3al/9GtAllN5hvkvYsxrlqIp9YBSUc="
            }
          },
          "J3/0iDuADN9vo4zqFyYjKM9W4PGEjAVoa3EMVfGedeQ=": {
            "valueMac": {
              "type": "Buffer",
              "data": "hRZl3aD+b66IcrH561OjbwHVlYhJYDPpWIgibrMLBCk="
            }
          },
          "KB2p1Wg+aYDlG0As8slhWC+sJsbVkHzd6719uo/INp4=": {
            "valueMac": {
              "type": "Buffer",
              "data": "QgE7gceuFro2XGtGl/jJnM7CkCcvoy8HZq1eFSQ3rFc="
            }
          },
          "KY41ZFPZSYtSexnNKi7eryDgReuFx/xZcAth+dW6E9U=": {
            "valueMac": {
              "type": "Buffer",
              "data": "e6bHbTE3iY2zdOa6UoLiKeIwK4jmz2Tj4olYfApNKnU="
            }
          },
          "K1G/2ABBhAdOEavbLdSjy5kc9Ft7umIqN/NALf+O5lc=": {
            "valueMac": {
              "type": "Buffer",
              "data": "GW8rEmXyFzsVu0aQaO8d4Tw2Vmtt4Av/f8PLRzG1i3c="
            }
          },
          "LCcVInjvDRldMNnGuDaI8ESUp1JLJG4r8+DDRgo5jF4=": {
            "valueMac": {
              "type": "Buffer",
              "data": "vXx+vaTgaTdciGfRmhctIFX7V3Jgb2rY4BWRHStjP9M="
            }
          },
          "LnD6JuoYqglVFKEF3WVSSPTGwTyIYIL2M+/IzyeOZLM=": {
            "valueMac": {
              "type": "Buffer",
              "data": "ioqg0Mdoi5OuQ+1F4VuAtGD4AvK4e37PCbH40ozdocg="
            }
          },
          "M9dEJ0GREYFHTLYR+K62Z5C+9aKZpefXW4Pz3E0QeMw=": {
            "valueMac": {
              "type": "Buffer",
              "data": "XSAJuQHJjAvZWI4QEcXqPtt9P/Snj3OZ99b0b6cy8WE="
            }
          },
          "NkOpqQeX05Ph2GU1ZWda3d35y7HPjVSuS/METMeYl80=": {
            "valueMac": {
              "type": "Buffer",
              "data": "8v7idtCu7H4r/ezWMAL9YwMSROTIOyfj9gmKOs0ieHE="
            }
          },
          "OH9a7+4Y9RBQeZ2CyO3+Sa6obG36M0Fg0gMP/Qf3fzc=": {
            "valueMac": {
              "type": "Buffer",
              "data": "I8TDnNOBE9qPkVnJKc5FHTlqADkT0hE0pakQJhhRkvg="
            }
          },
          "PBiHFgpLQjNEK5WIls8ebTjPpRd/fDSg93WL8s7I56w=": {
            "valueMac": {
              "type": "Buffer",
              "data": "jspt+LhsNzsUcdJqxgcnXgZ/vLwWFEVCqdMvIGNy+6E="
            }
          },
          "PSO7jkBljME1PiVu4Mo3ceG5rpBJvclrDzuo8C8U4iE=": {
            "valueMac": {
              "type": "Buffer",
              "data": "/yJAMhOGuz/OXEFh9R1JuRpdtW3AJrNMQeTpjxgHy9U="
            }
          },
          "PTaNRjil8Dt3WrOoUaDgvz2Om5QNMCYqFMtWAzmV+HI=": {
            "valueMac": {
              "type": "Buffer",
              "data": "vG5pTUl1fxY6ET8biFKkV1dZ7ztiYM2iOndu87xJcww="
            }
          },
          "PV3SAf/5S3mwpbnnKTu+Xwo128IPc6E357IpE6Kpkz4=": {
            "valueMac": {
              "type": "Buffer",
              "data": "3bPMV9kB8wOtmLzWwZwwWsVlXWAX404S/8dea1InEaw="
            }
          },
          "PlwlzKr8RLCIn5bdTwKhpWO+uM8zlRRc6JLqMdeLiXo=": {
            "valueMac": {
              "type": "Buffer",
              "data": "/E9StYog2ICCU+TCReij9+sp4fd3VFLMqcaavZlwbbM="
            }
          },
          "Pr+0vXLnHJ+n6jV2IOsVwUlIeLcjQoDQeWNRTRPTGgc=": {
            "valueMac": {
              "type": "Buffer",
              "data": "48oWOdFPmnWssJDof/y9z3HxSjw5+GoHxMt8cnV2zn4="
            }
          },
          "PuoK7EJjaR2Bbc0VhC2xKHsgWbhW1BZEXK9wMIQt6mU=": {
            "valueMac": {
              "type": "Buffer",
              "data": "eGy2yBz1he54XFjVn5OjTE5ZURhk6a0C3VbFYtBCNEM="
            }
          },
          "P2tm+sSJYt0zuN31BQC1JNcnB0bt0r3aLtYeu/4mESI=": {
            "valueMac": {
              "type": "Buffer",
              "data": "BKuzFHUVZvPsaYOKpI/Q6a27IzLM/lIVq1iTe4Y4Nrs="
            }
          },
          "QV5l9VDAJTKF/rWrUlSSq8TseASDVrkfyTEJREJbdt8=": {
            "valueMac": {
              "type": "Buffer",
              "data": "HZDfq3Em1RASABgqauUq1xBy4y5ZkkOYmbk5lXAVJsU="
            }
          },
          "RWO2VQAUKWyieKJBJhluujB2AEw6pyO8yFbvkdLnLhc=": {
            "valueMac": {
              "type": "Buffer",
              "data": "zOeKs4yBtoeuCzkmx1gijtU7AZ/WSxaAEtBQUwuIoFs="
            }
          },
          "RdfaZkOMSBqYFNpZPumHIQOB7xpZWMf+qYl3lCh7s0s=": {
            "valueMac": {
              "type": "Buffer",
              "data": "QJfO/yQCneESBGToYE9NO7GAQmbCcip7UfE0rDpNI4c="
            }
          },
          "R+ukRxuXN6IDql6Q0L2npxBMx+fFjSA0FclobwSwV4A=": {
            "valueMac": {
              "type": "Buffer",
              "data": "tn7LYfLqI+iyiTxSyUoWX5y6MdraqMY+LfZmeY3MzsE="
            }
          },
          "S0af718/CKUHTd+lzBMlRgxIebyDKg6E+IOcH6rauu4=": {
            "valueMac": {
              "type": "Buffer",
              "data": "2DR2sYBaU9R6hEZxsSI3kGltJgVfIOT/98Npn3Zjkm0="
            }
          },
          "TxGxRjH85fNijZOhpbtXvxai5aJFDGAK9L+OlkvLyeM=": {
            "valueMac": {
              "type": "Buffer",
              "data": "6wh08crhQP2orbkJe7gcJnSSLYSsRgKtGZUwMmK0weA="
            }
          },
          "T5k2x3pAdY+OqQvP3rRDwGjm9NXfoGpDwc9w+OKYv14=": {
            "valueMac": {
              "type": "Buffer",
              "data": "91lotrs4E010sJCixAB01WcWNkGOIGZbbP6D6/UW8gU="
            }
          },
          "UsgwDxIh3aVTPujj5K574me0HDrEnqyg685D6IYRiWM=": {
            "valueMac": {
              "type": "Buffer",
              "data": "HAj8C3WGF5kB4LCPt+sW2bwFBGMWo9YeKKlU+WZ+pTo="
            }
          },
          "Uv1IlAqZNkqcoof1QshqVajJub4ft5rCOzl1TC6i/eI=": {
            "valueMac": {
              "type": "Buffer",
              "data": "qb9bOz3s+XBc2YL6Tz02pTEM0DUtXseVND1JCn4mPk4="
            }
          },
          "VMdlLbJX7FDMugXO7fieDZVuurI3x/6gTePw9Ph/bN4=": {
            "valueMac": {
              "type": "Buffer",
              "data": "7VXQLoncI2Frp1FNlhVCA0zCkVuO5VQcTM8ENuE0gTk="
            }
          },
          "Vy2a4cQu6iMxiV2jeXZr6KTgr56PcsqA2uAdfEvfdFo=": {
            "valueMac": {
              "type": "Buffer",
              "data": "TJM1ZSPufaSRuBuKKmGPOD2AxDmfQgJ/4xMZeQNcZDs="
            }
          },
          "WAPRI+0SXeR/bPy6iXF3VveZ0ZuLxb4BiGafcvvjLkw=": {
            "valueMac": {
              "type": "Buffer",
              "data": "xnJI5W6fm55MMkMAfpiLGihUz4Ac4MWvGPDoI71sU0U="
            }
          },
          "WopHpFLzGZsPbu1sTym2VerANvOvgE5B5Tb2kEDMi54=": {
            "valueMac": {
              "type": "Buffer",
              "data": "Iq7KhlrOXaYzYFHa4umluadbjnxKHU3PB42kfzUQOCg="
            }
          },
          "XL+mmQhzEk9fK9H++STtMTo2OzdoTIzVmpVJPYZZIZ8=": {
            "valueMac": {
              "type": "Buffer",
              "data": "Gky7y1T/wq6NKHT+mvGsPyhb6B+Eg4MQg7jr/uXbJJY="
            }
          },
          "XbE8ZmtsNlwmjhWPsRbDg8Y+HzYGnAQ3HzTPW90suZY=": {
            "valueMac": {
              "type": "Buffer",
              "data": "sj+0hXQT5dW8LDr6+L0fpUh4O6fIjdfCGAAPtgGcBFA="
            }
          },
          "ZU/M4PaqFxnu0Bm2IVpxhcZL/cg3llN8g0PbPGHNSAs=": {
            "valueMac": {
              "type": "Buffer",
              "data": "dmfG1pnBnbonSpssu5x5cb+YAsf348eTj7Y6lVc5FYw="
            }
          },
          "ZeKPEbMFHRx27BP7UepT/wUfZvmybR7U78H2nfX04EM=": {
            "valueMac": {
              "type": "Buffer",
              "data": "XfbKIRRZFB9ZQWnsQ0GXihb8vTSTName0uEZli1Sam4="
            }
          },
          "aMyEdZZgjBnF2Hh0d2/5XrHUDOkUXN8fh3O8se1N8Ow=": {
            "valueMac": {
              "type": "Buffer",
              "data": "Jsg4b+vr46sYUFh8xpVCd3YUQQTnf1WworVC5sorYp8="
            }
          },
          "a2ulNe18kUTJ9n9u1wbKjJIhg5Rw4NIugoQ8othIDQ0=": {
            "valueMac": {
              "type": "Buffer",
              "data": "XL4Oa9WYxA9pBNQCzl7VuL0Q0DYRC43ZXQxSc1nEk1Y="
            }
          },
          "bBhudLzPfkV7qfNj6iWBp+YCT801LbJQjZ6xP7uUJ0I=": {
            "valueMac": {
              "type": "Buffer",
              "data": "nGS6vsRfMYhtM15ra5aijrFkzBUdAkbRj/Ez3jurji8="
            }
          },
          "beIH6gIlHaqzubbYjC1lDPAi/aJVuoACtKtLrlRW4qk=": {
            "valueMac": {
              "type": "Buffer",
              "data": "kHsNFsVKUVRD9WlW52oPOlTATph+U4NAMDsUB2Q/6n4="
            }
          },
          "b3Xv/NRPEIjT6Ishc4V6yo9tBfHJxF9Q2ft/aV1Gfug=": {
            "valueMac": {
              "type": "Buffer",
              "data": "kjebO4V3t6Tf+jvpQh+CYixxp7eN7e+TZAywJMsFKXw="
            }
          },
          "crfgXcmJiamEvoQcaGuWcDnhNeSm/VLsAfR77Q7QhBE=": {
            "valueMac": {
              "type": "Buffer",
              "data": "vwMKYMOPHnnxdS5ZeyvyqbBvv6ywKAPARuCnb3UyyRs="
            }
          },
          "dE9J2MKKAjl8V6g+ogIJ9flq446wmqmBKkLDHodizZU=": {
            "valueMac": {
              "type": "Buffer",
              "data": "XsOw7aWLgJXRD5lU99Wl8b1H+44OEHTXSwU9Yg+GsmY="
            }
          },
          "dTUhc6ctkfFK3pz+9T+tqhzO3RJHWEzihupRvRV40rE=": {
            "valueMac": {
              "type": "Buffer",
              "data": "XKeZrLRe8xKGUubhgVRTGGKYi1kXxfR+i+c2KbpIQ3k="
            }
          },
          "diuQuN0rDVMzqyngFtZUhf+0U0hblil6xbNgcdg+E1Y=": {
            "valueMac": {
              "type": "Buffer",
              "data": "yAncYzbDF7+CJ74kD0nMdzhHzUci8B38DWG2sNCCXlI="
            }
          },
          "eipqTOoz2qqe0LLsuvGehWgwtG4Y0ZIHkuB/Bi/doR0=": {
            "valueMac": {
              "type": "Buffer",
              "data": "qiqgvHyJiCx2F5ieE7rz9I+bXYE7xCvEobmlL8R5o3o="
            }
          },
          "ewj+W6fSdKZ/sXzSw8R4FE38KqouVby1Sr/DL09MoPY=": {
            "valueMac": {
              "type": "Buffer",
              "data": "NlsgDs//zCfPyNGdKBkG8PKfXv9qijJdbsr4+soiWrE="
            }
          },
          "exYCZWCaxz72dASy9lRSwa31JRT0aXpP88Cv5F3Es0w=": {
            "valueMac": {
              "type": "Buffer",
              "data": "XQXjh5AE05999JyQJKsiwFG31euW3t5JVtl/ifg8uro="
            }
          },
          "fJpaxncWYfN+u7elKXk1rHQNLVG0g1l3P+k53RVULNM=": {
            "valueMac": {
              "type": "Buffer",
              "data": "RtxkwrArqcNvpkjHOcGPupstJGGsQHW//dX7XJF6h40="
            }
          },
          "f1SLwnmhyNLIB0LDH5WYL1laDKGWCJSwT8KQ3vrARg8=": {
            "valueMac": {
              "type": "Buffer",
              "data": "LgkGvAtdMzaynG7oxiTJqLbohL7ZUx2dzX5z7PX1nSM="
            }
          },
          "gvfkoMBWuq1A10uiVMqTWhXxeeJhc3gVstogszj5oI8=": {
            "valueMac": {
              "type": "Buffer",
              "data": "Z6vcAOWI9P5xmc7EcAsUqFDbUPygX0If6pjGyuCGLkg="
            }
          },
          "gvz5cTQGrubBG/da9lWOZJFVXeHms5EAcvsfKuAdniU=": {
            "valueMac": {
              "type": "Buffer",
              "data": "VvuyR6TjlcdxL2l5LAq2bO48QhBcMuVdzm4z2r0S3Sw="
            }
          },
          "gxQfYcPChsO/2bLB5m7T+BNiprB/iVenUyKCjfsL6/w=": {
            "valueMac": {
              "type": "Buffer",
              "data": "EwqBlCvJfttl5QJHyrt5+MV1eXA1FWVA//zJ7QoZ++o="
            }
          },
          "g83IRFtDhWCaJajSYWPpR6fXYW4Zz4BPj3lIQ0Pvwak=": {
            "valueMac": {
              "type": "Buffer",
              "data": "5vF1dWklNatqtO96gbERvCv/8hZyu8C26g/ZPMmIe/U="
            }
          },
          "hcpjC8eXVOdKYvWgFRNeW79/hnlZKNRKI14TDQ+jEYM=": {
            "valueMac": {
              "type": "Buffer",
              "data": "I5O1v23m++Uc05sS1ANgw587IoTxEnUQyK8r9l4UFQI="
            }
          },
          "hvXrwaMYN2QC72uFod/s12EudBDNqAFzJr3QyLtb5HE=": {
            "valueMac": {
              "type": "Buffer",
              "data": "3620YAXJ30PnLtJ7qlto/r3EGKNkd22I0Q2zHtkMpNs="
            }
          },
          "ihkodm0vNWEdjykq85pt+cDQTL98t59saAFQP17GajM=": {
            "valueMac": {
              "type": "Buffer",
              "data": "yhOi/zxAQnRmFRGmHQUSSeBWGlA5PGR9YzgtnwelnSE="
            }
          },
          "jA30LWdJ0TKrfJi7qdhum4BMzFlpQZMOv5n7tUObQZw=": {
            "valueMac": {
              "type": "Buffer",
              "data": "zN9vmOOzUTzHUKbNkPMqXubt5g5S4f+dn4PkxPr6M5M="
            }
          },
          "joSxcop0RTOmBSBuRL+gbcotqFsARiE3B2ahxm1rHAY=": {
            "valueMac": {
              "type": "Buffer",
              "data": "DC1PFP/MsqA3xDt/cWDQQ7DjySbzk9iBek3mIvEbLd4="
            }
          },
          "jwM1HKtL6Md9RKsatYrAdZ8LGX87Xv4j/d9NLxwE0u0=": {
            "valueMac": {
              "type": "Buffer",
              "data": "y+U8oAqW4zwclR6seC2nqcsWN6DbyxOQwXYvgDgxEgI="
            }
          },
          "j0Woeq6r7hYqoBoZnVGlv7PxYU4EO0HrC9YZ8cG6/co=": {
            "valueMac": {
              "type": "Buffer",
              "data": "W9RBupz/ajE0awZZ5GFVMbwRTgNXwGQVQ7K/SaD7aJE="
            }
          },
          "j7O9cREtRgvEQGWOJgv+TKnNp+VPNqDxJPAHak2RFIo=": {
            "valueMac": {
              "type": "Buffer",
              "data": "50pe8+Ded9jDdJMNWARQ//C0vLvCF1UcU6zp4BfIHl0="
            }
          },
          "j7pD4qy756UpIE+gbrgETQ2PoYf0Bz8vR0sc09Pptm8=": {
            "valueMac": {
              "type": "Buffer",
              "data": "k8IrBFjYxNUwZbkFxmMuV0crjasjCnzIidZUbiXUCn0="
            }
          },
          "k2w88bK7e1lr4MS3oDV3awbv7bhbIq/ZkauP1gHbC1c=": {
            "valueMac": {
              "type": "Buffer",
              "data": "XQZR8eC7hLldXQqZcifpPcEH2YKeavg/cNeEAaG5GEE="
            }
          },
          "lAsBVyMCDrJQoK5KtrvP2LdWZt2MsdT2WyGOFS/xACU=": {
            "valueMac": {
              "type": "Buffer",
              "data": "wfY4PaJLsIxMHy5/SX2X7ibRNf1+zbfe6QoA1UH/ynU="
            }
          },
          "lJ3Vm5woCAJzTBFQXbo+uoRgzIN/T23ymoeMez0/fCk=": {
            "valueMac": {
              "type": "Buffer",
              "data": "TGZi0N6AJaZmbnRy6NhoFddeHxv7UuYM6LKUN2wnzHY="
            }
          },
          "lUqxeS3ckQSlc9poTNIYORyLpEAgB+KneshjeLW62I4=": {
            "valueMac": {
              "type": "Buffer",
              "data": "8kGSlho7ZE78FhZ+vwSWEK+fSx3WxzFnxxZ+tK6RwLY="
            }
          },
          "ll/LCSzEHrAZEt1egpUkNMy+QCbaP42oCGk5IutDanA=": {
            "valueMac": {
              "type": "Buffer",
              "data": "LwwVCIPZCfX0Z9YcnWytpD9Yefq9wMga68gZDJlU98M="
            }
          },
          "lmMaWKG36l+2tOcVJ3aH/VFQxwv4W0WAb8GiSgCXw0I=": {
            "valueMac": {
              "type": "Buffer",
              "data": "Cx7qwnZqKXkrELNuOo4lMBvOuCO+bRTG48Dkh/hujQg="
            }
          },
          "lvic1TY7wVaziwNz6fF8vTtvgOrt8hUWOqXgXNwvHf8=": {
            "valueMac": {
              "type": "Buffer",
              "data": "EI1zdI9SlY0foWouREl9hi1bkrhvpifrS1gqH+grfI4="
            }
          },
          "l2RtLH7Wpe9OeGIOOzANH4avDxcTo7EmAtI1lsaaJzo=": {
            "valueMac": {
              "type": "Buffer",
              "data": "kLkjrvZPLPNOjRF3FulwbGIkwRN9dJP9hzc1qSefPfg="
            }
          },
          "oRJn4nNnt+RUkSSp63nIbHzqoquKNnGAdQ9/s0fN/MA=": {
            "valueMac": {
              "type": "Buffer",
              "data": "MuzbO98GpWvstTF3pXS6uYEpbT38yyYlx8tgg2s0vnA="
            }
          },
          "pjamwwZaa7vtzycnhSozm/xq6qnBIAvxQM9mlpOEzIU=": {
            "valueMac": {
              "type": "Buffer",
              "data": "jT76jE0McY2Dp1uxUS7mcejWhepQNjBTNcnOoBmSmns="
            }
          },
          "qVLR6VZn1crEdvYjAArV5VrRNA9m9+W2adrWzvAVJ9I=": {
            "valueMac": {
              "type": "Buffer",
              "data": "pQz10CA9/K86vpGCX9HG6wEC8GNNTHwgUS2k8Uot9lM="
            }
          },
          "rJtfDSRdY5UNYhSCut+SjWImJkoU4KCeC05DbHAAweM=": {
            "valueMac": {
              "type": "Buffer",
              "data": "6Wmhs/VKzc6gwi6OpJVjDlCWkNtzLVh9k3ROFqZg5cU="
            }
          },
          "rLe5VYaj77GHWHIxh5Ga0hrBiVB6aXrAJ9uMHd8cBlk=": {
            "valueMac": {
              "type": "Buffer",
              "data": "y8Tv5ERG/E0e6NRjwDzFTz+w18lXFsxO50sNmSxfHPA="
            }
          },
          "rjtpGASjWPfPOITwujJW1Y27/Hdi0AaMZch8hgC8cTg=": {
            "valueMac": {
              "type": "Buffer",
              "data": "+qsoKHzqZuXaVbDPhX0fAJR37+2eGEKl+Y+831LURFY="
            }
          },
          "ru8Oz2CtuiNMnw5yxx2LbnQ9fEm5jJlpQygOcW9AVZc=": {
            "valueMac": {
              "type": "Buffer",
              "data": "7t/891y2uh5bZrwQUcHSRXrtM4IXx5EHZnz7CY4chwk="
            }
          },
          "r4H9dwWBansphIh//xkWZ+URbKk7nG1EsPqO0/h9Wf8=": {
            "valueMac": {
              "type": "Buffer",
              "data": "BFSrx9HBhtcJCJd9f6VKMSQmGblxAS53D/F5ngLor38="
            }
          },
          "r9rTSHgRRjV8o/eYLgzNUgNV1kfHDVdGAaG36YyA+yM=": {
            "valueMac": {
              "type": "Buffer",
              "data": "FiqaeoYKq4KW1I105S3oDOroMYeNRwg9UuJsw424UdY="
            }
          },
          "sm3r0uz8j/Wp4Y49ed35ORNwTjTfaFaX1adAsSGliaQ=": {
            "valueMac": {
              "type": "Buffer",
              "data": "G3GNKr27flFK4vcEEP/ls4FlJBzuZIvGO8lb3tSGjFI="
            }
          },
          "sq4hJJeeA16v0moDlTjIV8eCI/BjrV+G+KjEUZbzIjg=": {
            "valueMac": {
              "type": "Buffer",
              "data": "HXZf92OrQ1Mf676noqndNZUIDX6pM6WaPBNOHqG8TmA="
            }
          },
          "tD2k0kRNMBBM/6H9XbxXHuoVmfUjFCLvcHlKEEfb+B4=": {
            "valueMac": {
              "type": "Buffer",
              "data": "09F2jEJuT5R89QCwO9MFk/58tNBY2W/ouTEzXhNUgfE="
            }
          },
          "tYN0+3+ODrhLhreUFGn08fmV0qRSs3WpuT8kGQVxgqQ=": {
            "valueMac": {
              "type": "Buffer",
              "data": "Fi3Ee+0b0EB5YoVgk/El85b8oPHGTiac3Vkruy8nmxA="
            }
          },
          "trI3OwZB5kObUMazoVDhQIcJXRWHOG9f4E/9ZKIrB7Q=": {
            "valueMac": {
              "type": "Buffer",
              "data": "9GwH46UkG7O4v709Afrrhf+ObMPZ3BAQi/JaxOSX1IY="
            }
          },
          "twEsVF8pxeIguTsa0JmxqN0ybtUpvvvqQIeUl1oThHM=": {
            "valueMac": {
              "type": "Buffer",
              "data": "xQ779BhvCNghm9FMOUybVtT9CClc+IS2sCOfomV/u5M="
            }
          },
          "uJfp+ulLuBuDQkztuFjwmGwQflETMXQceiz5hCMocCs=": {
            "valueMac": {
              "type": "Buffer",
              "data": "tKxch04sXwLmCvJf35ZNvtKgdVp36raaauNM5C7RZNc="
            }
          },
          "vzhXkZYiRMr4d6jHjC9vTFBEtqj9tEAUF4rs9GVQD3s=": {
            "valueMac": {
              "type": "Buffer",
              "data": "dnWfNEbGFby8VfOQ5B20Z7dMfw/jcNGF/OdPj44erAk="
            }
          },
          "wlhVvuanoiw8kSi1oLwPJgwPnqkuoqbNaiczawTTLs0=": {
            "valueMac": {
              "type": "Buffer",
              "data": "a9XGtZ3TRmfuM752NY9JAe9bP9hXNL/U7Vwo75NFbBU="
            }
          },
          "xdtM6mErGL9GbPp9kcz2TmW4r9rPNyY/uo2VZShluzY=": {
            "valueMac": {
              "type": "Buffer",
              "data": "K7YV4u1cifhVsqDvyImNzIoDqmdHF2pZ7qSUBOSQc5M="
            }
          },
          "xgw+CTuMHt5WsQfE8/SebeZGsm9uAT5nyubynfAV3NY=": {
            "valueMac": {
              "type": "Buffer",
              "data": "0wnIkBYHnUa1lSS329w6GIfGmy2e0oGEncRyQVxRjzI="
            }
          },
          "yquzN+441cz6BANw0G6mzueUXoO7yIUv9Kc3U2kdQjk=": {
            "valueMac": {
              "type": "Buffer",
              "data": "0fKLUQfyKSbFIHUP2Al+Ckjr04rc/V2jx0BiBLe6ly8="
            }
          },
          "zL56GKa2eO6etnEEA0f0WNl5T06Q87NLe0aFASdCDTg=": {
            "valueMac": {
              "type": "Buffer",
              "data": "kt0y5D92kRsZcctRtrUV6aVi9n2HH44R30rDw8EhuRg="
            }
          },
          "zWd5xjkG8dCj0aja2/PYO1w/d5HkOFhTBHJQ5Dk1GL4=": {
            "valueMac": {
              "type": "Buffer",
              "data": "ajTq+tkV3HUAbIziCSi90hJ+ZZtL0uCQVvwSDB2dxzE="
            }
          },
          "1IAJ+I3dB5iJEX+0t8W4LH0WcagDFWi9+p9jpd+psO0=": {
            "valueMac": {
              "type": "Buffer",
              "data": "olQTFp3LsJEs3szaEcvx1Xe3oOapdb2CVFiVketzcL4="
            }
          },
          "1vsAlecsMmz4LcRKfQMVM1SPWkfkVzs2e5m88igbK6s=": {
            "valueMac": {
              "type": "Buffer",
              "data": "S08dvS0bzZhOijm0R2JpIGGg4bxCeHJzMTFL/exiGQA="
            }
          },
          "16CV3vEM0FOdVq4BY1d5B8FLzKLJsPuz6uJ0GyweyRY=": {
            "valueMac": {
              "type": "Buffer",
              "data": "qw9a1wkxzBxEnF0hXu/Egqd7aCw1e6MhpmoBS8ggSmY="
            }
          },
          "2G82B0lATim8HlsXgymOBrBM4J+MR3mMF/1ZlkS/Nms=": {
            "valueMac": {
              "type": "Buffer",
              "data": "huvJ+XbcahXnIty3X5dO8feEsPwRxU/7GYES74BzF+E="
            }
          },
          "2tTcWAp7y675OSHGX1um4HptI0zuq6vPL69Mvr6N0i4=": {
            "valueMac": {
              "type": "Buffer",
              "data": "ThSSHiXQztr92u+INRPLzk4UkLrN512AZOnijP0el20="
            }
          },
          "2+7NrjaG4lou1hfZbJrX8MIRATHmczx4YUV95rx/5DI=": {
            "valueMac": {
              "type": "Buffer",
              "data": "/Bzyxv3HSRWPTkXzGA8LBTFI87fXkNF0AhlezRqP5is="
            }
          },
          "3duLeW5FWviPq+bfxouIMx+C9YLOt12ZNol7QgeviFo=": {
            "valueMac": {
              "type": "Buffer",
              "data": "Yu2YBqX1IaU7hclfbl+YNypRRTo9radjJOqe+LL0PyI="
            }
          },
          "31WUpWJdvQepWmJmwKflLUsjZVkzEjVSVSux7Mi3RXI=": {
            "valueMac": {
              "type": "Buffer",
              "data": "jSYwXuAUGgTG6cDdqlVYHLmcFHkTxxzeaAIDZCN/fG0="
            }
          },
          "4Z/noJJSs8pRB+8NcxoVvpA966TAw0aQiiVIY1R37nA=": {
            "valueMac": {
              "type": "Buffer",
              "data": "Q91zgBqvrPzJ2g3UWlgQ39APo8PAOkD1oHFFC3g5lfM="
            }
          },
          "4kAX0zNOvZ9wlutMHwG2dU2634FQxK5SFv77CV++dd4=": {
            "valueMac": {
              "type": "Buffer",
              "data": "7LILPhfSATlIhpXorG6/jVQeFddCvOfSO+JZTib7a28="
            }
          },
          "4qy6rgj9fTzkYRLfcPQlP8wld4PXniMglA3Im40YeiA=": {
            "valueMac": {
              "type": "Buffer",
              "data": "4PMKOQFoflT4AMjAH/mCNp7DrDixFDkix18z4CLuuuk="
            }
          },
          "4uIe8PVBbARj4HaFtYT+Qo8hpe+tRMvIw2DUkfLHOY0=": {
            "valueMac": {
              "type": "Buffer",
              "data": "8ptFjFKhr4TEb+kVsyvXbU0InngxihQxaAYqdFs35KA="
            }
          },
          "43Ya01pFFR5Xd9oI3yMOYK33xWFNqQGanSh1k5FdvVc=": {
            "valueMac": {
              "type": "Buffer",
              "data": "EF9WMBPOkZDRgjBnLIPwoRymEICPRbpv20Nyi3Rh9HU="
            }
          },
          "5TStalTMN4JYUp8EjYY8JKLoQk+nFBSt7kuL/NwzFwY=": {
            "valueMac": {
              "type": "Buffer",
              "data": "Xz+RkMkmPFjs8hx/GBVfglH/X3U5JPqdW1Sre/z2/NU="
            }
          },
          "5bUrsSUiErTyfrCrxoHPJg9xP68EJJbIhHf7cQRxpGs=": {
            "valueMac": {
              "type": "Buffer",
              "data": "O5GbH5BMljaPvyYla6tNGsrqlnOVqR0WhdbGN+J87Uc="
            }
          },
          "5hFcQ3QLrsAkLWjXdHEBo6mxkkQ8IMRLbBQF6IuoNmQ=": {
            "valueMac": {
              "type": "Buffer",
              "data": "IJ/u56PtPnYM2swuQZaYLTgg7cqzEa5e9JXU0FslonA="
            }
          },
          "5oTrNZdhtoZaVVNHatr95Qs2kacF8TLi/cPRbgR5OEM=": {
            "valueMac": {
              "type": "Buffer",
              "data": "PoIDbhrTRu8W4CkG+1xVz/Ll2tSuMrZqnwZvr8z1SXI="
            }
          },
          "53/dt13qtArkiJegPEeJ9x3zSDsFdOyMno4ODlmZRc0=": {
            "valueMac": {
              "type": "Buffer",
              "data": "gw7z2E3zRjTHgwQHmXzjqotaSju3+hiZO6Vpl198OPc="
            }
          },
          "6IxNO5e9bigdj3dbjpeM+cmH4X0ltosbWxWXBXWnut4=": {
            "valueMac": {
              "type": "Buffer",
              "data": "oIJ6oQfaIyc3v8jldAi96jm5Ez/48Ntw2VK1sOISc+8="
            }
          },
          "6JGzLNyjv36UcKDjc251yp1wGMiIHYfViUzTJGxBQlQ=": {
            "valueMac": {
              "type": "Buffer",
              "data": "uovOrulWugv8jN3YlBrO3DLEbj4p3Gd7QT3NRZ2nlYk="
            }
          },
          "6anleuO2X5y5kyWpKXaFFYVBxPMq4D2u9kUU209X1ck=": {
            "valueMac": {
              "type": "Buffer",
              "data": "ZU7IYCdwc5mJ9urhr+orIiFaWOvlc85jW4XAVfJHvHU="
            }
          },
          "6oQOmYlUydzu+Eljnqvx/Zzu8gSoPJMt0ygS748znZY=": {
            "valueMac": {
              "type": "Buffer",
              "data": "knKvSNbjAB/p3yKK/UV/OdQD3sfHRwCZK106c37ZlOA="
            }
          },
          "7V5Iw38JeMOxd3rAPTP0zLPHzrL0OK6X/WFUNFYAB2o=": {
            "valueMac": {
              "type": "Buffer",
              "data": "pksV4vS/KR87+UEhMIekZRLFBVHZE4MB2tTOnG0/4DI="
            }
          },
          "7W8yTZmNUF4VYlnNwld555Q0wfqzJDTqlgs7v18BXLU=": {
            "valueMac": {
              "type": "Buffer",
              "data": "DnTsEcIY2tOW20e0W4/KGWQFSEmYcl+imMc5lZ9j/tI="
            }
          },
          "7pCgIg6iI+ZkrzdVszZ2aFRG2wrze6wowWBVF2dy3iA=": {
            "valueMac": {
              "type": "Buffer",
              "data": "loRQ7FDA8atlOVuyoUa+K4T07m0cf7PJhGTRy8hpGIU="
            }
          },
          "76lw4ojxmfUJkH6jB7L/OIElM97OUJfDSZhxUA004Js=": {
            "valueMac": {
              "type": "Buffer",
              "data": "bEm/XPWBunG8NpaMXXPkbEhzBQ3OZ9woPuVn0kBqJno="
            }
          },
          "8Bf73/R7bIGpXXfGrSaEQ+6klDfUPqE7zdNejOBpinA=": {
            "valueMac": {
              "type": "Buffer",
              "data": "SdnOW0vD/a1CthDzsWIMVcz1a/gBAbBQqkfcpiD6K0w="
            }
          },
          "8KQ6v14XkaBijzBqycgjjKTrIxYbQkf+2nj0vIq52qU=": {
            "valueMac": {
              "type": "Buffer",
              "data": "KumbhUo8bQiQ0IeX+iYGIAAZnWc6c/AHn0mFMUVJQls="
            }
          },
          "8LzhMYGPhAP/Jj6uI/xufKEu2mFnTcdpF8WnzLODUZc=": {
            "valueMac": {
              "type": "Buffer",
              "data": "FeuxXzniYcOJN47DV1j/otNJwcN9X+CR5Gqj+A1D7iU="
            }
          },
          "9JyyvVCIviGzDBAjs0OdF663yWNiICCTxM+IleWH35A=": {
            "valueMac": {
              "type": "Buffer",
              "data": "ZW/zc0L6/xzVgL9fuJxHmgDBHtAClv6F/2An9Gk22tE="
            }
          },
          "9ou+vBWv60Pls+2zOewADn3ct9whjAwyEsSeo5MLayE=": {
            "valueMac": {
              "type": "Buffer",
              "data": "D68ALmtbVLec/diExyuWlP9y06R15zmPb+QWWFKCsOA="
            }
          },
          "981ugNJTsr1bvgOPw1CYsLCqfkLgQqHh8vdohscUcFk=": {
            "valueMac": {
              "type": "Buffer",
              "data": "+ePU+iJzllk7Cpz8S95QX0hfmQ3pVCDWjQVnVLBa3kQ="
            }
          },
          "+AY0pyJ3sN22ozmZadXEUcCIhoiM7c0aw9pjyTkrxvo=": {
            "valueMac": {
              "type": "Buffer",
              "data": "SUYkvWo0+QnLx1RHCYLXtTutpKVvR022+LDPj3cHCVY="
            }
          },
          "+BsYUNpkwazpqu/UrbP5mRDA/ryUoc14KMBICO3eDak=": {
            "valueMac": {
              "type": "Buffer",
              "data": "G6c9FRrWq668tTzGae3mt2/HWFbyGNY6a5TP5l4wi14="
            }
          },
          "+nfEaw+bBs97/z3wmxT7XtxwaTWA9JOy7Uc/ACqedc8=": {
            "valueMac": {
              "type": "Buffer",
              "data": "aH9LV6f21e/oKVN0CItsOVvX4WNeXRg/TAEKpLKKvZ4="
            }
          },
          "+9Otk4qxZCyIUjml6lp6IklamTxU4Fn87kJ+dlZ2Cu0=": {
            "valueMac": {
              "type": "Buffer",
              "data": "0Dod7yg7YX+EbrV/RNkjFjphICLlABi3V6dpMY3Qv8E="
            }
          },
          "/pjQ36y41I89zGNYPrOXNEjVaAqcCa/VlxeookX8bLs=": {
            "valueMac": {
              "type": "Buffer",
              "data": "sotREtfTgfdUiMnOXZXOn8NuwVbwnoYe6rFYrH1BxlY="
            }
          }
        }
      }
    }
  }
}